artemis_mcp/__init__.py
artemis_mcp/__main__.py
artemis_mcp/server.py
orange_artemis_mcp-0.1.6.dist-info/METADATA
orange_artemis_mcp-0.1.6.dist-info/WHEEL
orange_artemis_mcp-0.1.6.dist-info/entry_points.txt
orange_artemis_mcp-0.1.6.dist-info/top_level.txt
orange_artemis_mcp-0.1.6.dist-info/RECORD
